{
  "SportsActivities":
  [
      {"WordPhrase":"Football"},
      {"WordPhrase":"Basketball"},
      {"WordPhrase":"Ice Hockey"},
      {"WordPhrase":"Field Hockey"},
      {"WordPhrase":"Soccer"},
      {"WordPhrase":"Swimming"},
      {"WordPhrase":"Cricket"},
      {"WordPhrase":"Golf"},
      {"WordPhrase":"Bowling"},
      {"WordPhrase":"Volleyball"},
      {"WordPhrase":"Boxing"},
      {"WordPhrase":"Lacrosse"},
      {"WordPhrase":"Skiing"},
      {"WordPhrase":"Tennis"},
      {"WordPhrase":"Table Tennis"},
      {"WordPhrase":"Cycling"},
      {"WordPhrase":"Dancing"},
      {"WordPhrase":"Cheerleading"},
      {"WordPhrase":"Gymnastics"},
      {"WordPhrase":"Canoeing"},
      {"WordPhrase":"Surfing"},
      {"WordPhrase":"Kayaking"},
      {"WordPhrase":"Rowing"},
      {"WordPhrase":"Water Polo"},
      {"WordPhrase":"Diving"},
      {"WordPhrase":"Archery"},
      {"WordPhrase":"Wiffleball"},
      {"WordPhrase":"Softball"},
      {"WordPhrase":"Rugby"},
      {"WordPhrase":"Squash"},
      {"WordPhrase":"Badminton"},
      {"WordPhrase":"Skateboarding"},
      {"WordPhrase":"Rock Climbing"},
      {"WordPhrase":"Bobsledding"},
      {"WordPhrase":"Jujutsu"},
      {"WordPhrase":"Karate"},
      {"WordPhrase":"Frisbee"},
      {"WordPhrase":"Figure Skating"},
      {"WordPhrase":"Paintball"},
      {"WordPhrase":"Darts"},
      {"WordPhrase":"Escape Room"},
      {"WordPhrase":"Motocross"},
      {"WordPhrase":"Formula Racing"},
      {"WordPhrase":"Go-Kart Racing"},
      {"WordPhrase":"Marathon Running"},
      {"WordPhrase":"Cross-country Running"},
      {"WordPhrase":"Arm Wrestling"},
      {"WordPhrase":"Powerlifting"},
      {"WordPhrase":"Hiking"},
      {"WordPhrase":"Horse Racing"},
      {"WordPhrase":"Poker"},
      {"WordPhrase":"Esports"},
      {"WordPhrase":"Billiards"}
  ],
  "Status":"OK"
}
